newport_esa/__init__.py
newport_esa/esa.py
newport_esa-0.1.0.dist-info/METADATA
newport_esa-0.1.0.dist-info/WHEEL
newport_esa-0.1.0.dist-info/licenses/LICENSE
newport_esa-0.1.0.dist-info/RECORD
