Metadata-Version: 2.3
Name: newport-esa
Version: 0.1.0
Summary: A Python API for the Newport Model ESA-C Ultra-Resolution Actuator Controller.
Project-URL: Homepage, https://github.com/houlihaj/newport-esa
Project-URL: Issues, https://github.com/houlihaj/newport-esa/issues
Author-email: John Houlihan <houlihaj@uci.edu>
License-File: LICENSE
Classifier: License :: OSI Approved :: MIT License
Classifier: Operating System :: Microsoft :: Windows :: Windows 7
Classifier: Programming Language :: Python :: 3
Classifier: Programming Language :: Python :: 3.8
Requires-Python: ~=3.8
Requires-Dist: pyvisa>=1.14.1
